[
  {
    "origin": "OpenCV: Other tutorials (ml, objdetect, photo, stitching, video)",
    "local": "OpenCV：其他教程（ml、objdetect、照片、缝合、视频）"
  },
  {
    "origin": "Open Source Computer Vision",
    "local": "开源计算机视觉"
  },
  {
    "origin": "Other tutorials (ml, objdetect, photo, stitching, video)",
    "local": "其他教程（ml、objdetect、照片、缝合、视频）"
  },
  {
    "origin": "photo.",
    "local": "照片。"
  },
  {
    "origin": "stitching.",
    "local": "缝合。"
  },
  {
    "origin": "video.",
    "local": "视频。"
  },
  {
    "origin": "video.",
    "local": "视频。"
  },
  {
    "origin": "video.",
    "local": "视频。"
  },
  {
    "origin": "objdetect.",
    "local": "来吧。"
  },
  {
    "origin": "objdetect.",
    "local": "来吧。"
  },
  {
    "origin": "ml.",
    "local": "毫升。"
  },
  {
    "origin": "ml.",
    "local": "毫升。"
  },
  {
    "origin": "ml.",
    "local": "毫升。"
  },
  {
    "origin": "Generated on Fri Apr 2 2021 11:36:37 for OpenCV by &#160;",
    "local": "2021年4月2日星期五11:36:37为OpenCV生成，&#160；"
  }
]