[
  {
    "origin": "OpenCV: opencv2/gapi/streaming/source.hpp File Reference",
    "local": "OpenCV:opencv2/gapi/streaming/source.hpp文件参考"
  },
  {
    "origin": "Open Source Computer Vision",
    "local": "开源计算机视觉"
  },
  {
    "origin": "Classes",
    "local": "班级"
  },
  {
    "origin": "Namespaces",
    "local": "名称空间"
  },
  {
    "origin": "Functions",
    "local": "功能"
  },
  {
    "origin": "source.hpp File Reference",
    "local": "source.hpp文件参考"
  },
  {
    "origin": "Classes",
    "local": "班级"
  },
  {
    "origin": "Abstract streaming pipeline source.",
    "local": "抽象流媒体管道源。"
  },
  {
    "origin": "More...",
    "local": "更多。。。"
  },
  {
    "origin": "Namespaces",
    "local": "名称空间"
  },
  {
    "origin": "\"black box\" representation of the file storage associated with a file on disk.",
    "local": "“黑盒”表示与磁盘上的文件相关联的文件存储。"
  },
  {
    "origin": "Functions",
    "local": "功能"
  },
  {
    "origin": "template&lt;class T , class... Args&gt;",
    "local": "模板&lt；T班，T班。。。Args&gt；"
  },
  {
    "origin": "(Args &amp;&amp;... args)",
    "local": "（Args和&amp；。。。参数）"
  },
  {
    "origin": "Generated on Fri Apr 2 2021 11:36:33 for OpenCV by &#160;",
    "local": "2021年4月2日星期五11:36:33为OpenCV生成，&#160；"
  }
]