[
  {
    "origin": "OpenCV: cv::gapi::s11n::detail Namespace Reference",
    "local": "OpenCV:cv:：gapi:：s11n:：detail命名空间引用"
  },
  {
    "origin": "Open Source Computer Vision",
    "local": "开源计算机视觉"
  },
  {
    "origin": "Classes",
    "local": "班级"
  },
  {
    "origin": "Functions",
    "local": "功能"
  },
  {
    "origin": "cv::gapi::s11n::detail Namespace Reference",
    "local": "cv:：gapi:：s11n:：详细命名空间引用"
  },
  {
    "origin": "Classes",
    "local": "班级"
  },
  {
    "origin": "Functions",
    "local": "功能"
  },
  {
    "origin": "template&lt;typename V &gt;",
    "local": "模板&lt；类型V&gt；"
  },
  {
    "origin": "(",
    "local": "("
  },
  {
    "origin": "&amp;, V &amp;, std::size_t, std::size_t)",
    "local": "&amp；，V&amp；，标准：：大小\\u t，标准：：大小\\u t）"
  },
  {
    "origin": "template&lt;typename V , typename X , typename... Xs&gt;",
    "local": "模板&lt；类型V，类型X，类型名称。。。Xs&gt；"
  },
  {
    "origin": "(",
    "local": "("
  },
  {
    "origin": "&amp;is, V &amp;v, std::size_t i, std::size_t gi)",
    "local": "&amp；是，V&amp；v、 标准：：大小\\u t i，标准：：大小\\u t gi）"
  },
  {
    "origin": "std::unique_ptr&lt;",
    "local": "标准：：唯一的\\u ptr&lt；"
  },
  {
    "origin": "(const std::vector&lt; char &gt; &amp;p)",
    "local": "（const std：：向量&lt；字符&gt&amp；（p）"
  },
  {
    "origin": "template&lt;typename V &gt;",
    "local": "模板&lt；类型V&gt；"
  },
  {
    "origin": "(",
    "local": "("
  },
  {
    "origin": "&amp;, const V &amp;, std::size_t)",
    "local": "&amp；，常量V&amp；，标准：：尺寸（t）"
  },
  {
    "origin": "template&lt;typename V , typename X , typename... Xs&gt;",
    "local": "模板&lt；类型V，类型X，类型名称。。。Xs&gt；"
  },
  {
    "origin": "(",
    "local": "("
  },
  {
    "origin": "&amp;os, const V &amp;v, std::size_t x)",
    "local": "&amp；操作系统、常量和；v、 标准：尺寸（x）"
  },
  {
    "origin": "Function Documentation",
    "local": "功能文档"
  },
  {
    "origin": "&#9670;&nbsp;",
    "local": "&#9670;&nbsp；"
  },
  {
    "origin": "get_v()",
    "local": "获取\\u v（）"
  },
  {
    "origin": "[1/2]",
    "local": "[1/2]"
  },
  {
    "origin": "template&lt;typename V &gt;",
    "local": "模板&lt；类型V&gt；"
  },
  {
    "origin": "&amp; cv::gapi::s11n::detail::get_v",
    "local": "&amp；cv:：gapi:：s11n:：细节：：获取"
  },
  {
    "origin": "(",
    "local": "("
  },
  {
    "origin": ",",
    "local": ","
  },
  {
    "origin": ",",
    "local": ","
  },
  {
    "origin": ",",
    "local": ","
  },
  {
    "origin": ")",
    "local": ")"
  },
  {
    "origin": "&#9670;&nbsp;",
    "local": "&#9670;&nbsp；"
  },
  {
    "origin": "get_v()",
    "local": "获取\\u v（）"
  },
  {
    "origin": "[2/2]",
    "local": "[2/2]"
  },
  {
    "origin": "template&lt;typename V , typename X , typename... Xs&gt;",
    "local": "模板&lt；类型V，类型X，类型名称。。。Xs&gt；"
  },
  {
    "origin": "&amp; cv::gapi::s11n::detail::get_v",
    "local": "&amp；cv:：gapi:：s11n:：细节：：获取"
  },
  {
    "origin": "(",
    "local": "("
  },
  {
    "origin": "is",
    "local": "是"
  },
  {
    "origin": ",",
    "local": ","
  },
  {
    "origin": "v",
    "local": "v"
  },
  {
    "origin": ",",
    "local": ","
  },
  {
    "origin": "i",
    "local": "我"
  },
  {
    "origin": ",",
    "local": ","
  },
  {
    "origin": "gi",
    "local": "胃肠道"
  },
  {
    "origin": ")",
    "local": ")"
  },
  {
    "origin": "&#9670;&nbsp;",
    "local": "&#9670;&nbsp；"
  },
  {
    "origin": "getInStream()",
    "local": "getInStream（）"
  },
  {
    "origin": "std::unique_ptr&lt;",
    "local": "标准：：唯一的\\u ptr&lt；"
  },
  {
    "origin": "&gt; cv::gapi::s11n::detail::getInStream",
    "local": "&燃气轮机；cv:：gapi:：s11n:：细节：：getInStream"
  },
  {
    "origin": "(",
    "local": "("
  },
  {
    "origin": "p",
    "local": "p"
  },
  {
    "origin": ")",
    "local": ")"
  },
  {
    "origin": "&#9670;&nbsp;",
    "local": "&#9670;&nbsp；"
  },
  {
    "origin": "put_v()",
    "local": "输入v（）"
  },
  {
    "origin": "[1/2]",
    "local": "[1/2]"
  },
  {
    "origin": "template&lt;typename V &gt;",
    "local": "模板&lt；类型V&gt；"
  },
  {
    "origin": "&amp; cv::gapi::s11n::detail::put_v",
    "local": "&amp；cv：：gapi：：s11n：：细节：：放置"
  },
  {
    "origin": "(",
    "local": "("
  },
  {
    "origin": ",",
    "local": ","
  },
  {
    "origin": ",",
    "local": ","
  },
  {
    "origin": ")",
    "local": ")"
  },
  {
    "origin": "&#9670;&nbsp;",
    "local": "&#9670;&nbsp；"
  },
  {
    "origin": "put_v()",
    "local": "输入v（）"
  },
  {
    "origin": "[2/2]",
    "local": "[2/2]"
  },
  {
    "origin": "template&lt;typename V , typename X , typename... Xs&gt;",
    "local": "模板&lt；类型V，类型X，类型名称。。。Xs&gt；"
  },
  {
    "origin": "&amp; cv::gapi::s11n::detail::put_v",
    "local": "&amp；cv：：gapi：：s11n：：细节：：放置"
  },
  {
    "origin": "(",
    "local": "("
  },
  {
    "origin": "os",
    "local": "操作系统"
  },
  {
    "origin": ",",
    "local": ","
  },
  {
    "origin": "v",
    "local": "v"
  },
  {
    "origin": ",",
    "local": ","
  },
  {
    "origin": "x",
    "local": "十"
  },
  {
    "origin": ")",
    "local": ")"
  },
  {
    "origin": "Generated on Fri Apr 2 2021 11:36:47 for OpenCV by &#160;",
    "local": "2021年4月2日星期五11:36:47为OpenCV生成，&#160；"
  }
]