[
  {
    "origin": "OpenCV: opencv2/imgcodecs/ios.h File Reference",
    "local": ""
  },
  {
    "origin": "Open Source Computer Vision",
    "local": ""
  },
  {
    "origin": "Functions",
    "local": ""
  },
  {
    "origin": "ios.h File Reference",
    "local": ""
  },
  {
    "origin": "Functions",
    "local": ""
  },
  {
    "origin": "(const CGImageRef image,",
    "local": ""
  },
  {
    "origin": "&amp;m, bool alphaExist=false)",
    "local": ""
  },
  {
    "origin": "(const",
    "local": ""
  },
  {
    "origin": "&amp;image) CF_RETURNS_RETAINED",
    "local": ""
  },
  {
    "origin": "(const",
    "local": ""
  },
  {
    "origin": "&amp;image)",
    "local": ""
  },
  {
    "origin": "(const UIImage *image,",
    "local": ""
  },
  {
    "origin": "&amp;m, bool alphaExist=false)",
    "local": ""
  },
  {
    "origin": "Generated on Fri Apr 2 2021 11:36:33 for OpenCV by &#160;",
    "local": ""
  }
]