[
  {
    "origin": "OpenCV: cv::detail::Timelapser Class Reference",
    "local": ""
  },
  {
    "origin": "OpenCV",
    "local": ""
  },
  {
    "origin": "Open Source Computer Vision",
    "local": ""
  },
  {
    "origin": "Public Types",
    "local": ""
  },
  {
    "origin": "Public Member Functions",
    "local": ""
  },
  {
    "origin": "Static Public Member Functions",
    "local": ""
  },
  {
    "origin": "Protected Member Functions",
    "local": ""
  },
  {
    "origin": "Protected Attributes",
    "local": ""
  },
  {
    "origin": "List of all members",
    "local": ""
  },
  {
    "origin": "cv::detail::Timelapser Class Reference",
    "local": ""
  },
  {
    "origin": "Inheritance diagram for cv::detail::Timelapser:",
    "local": ""
  },
  {
    "origin": "Public Types",
    "local": ""
  },
  {
    "origin": "enum",
    "local": ""
  },
  {
    "origin": "{",
    "local": ""
  },
  {
    "origin": ",",
    "local": ""
  },
  {
    "origin": "}",
    "local": ""
  },
  {
    "origin": "Public Member Functions",
    "local": ""
  },
  {
    "origin": "virtual",
    "local": ""
  },
  {
    "origin": "()",
    "local": ""
  },
  {
    "origin": "virtual const",
    "local": ""
  },
  {
    "origin": "&amp;",
    "local": ""
  },
  {
    "origin": "()",
    "local": ""
  },
  {
    "origin": "virtual void",
    "local": ""
  },
  {
    "origin": "(const std::vector&lt;",
    "local": ""
  },
  {
    "origin": "&gt; &amp;corners, const std::vector&lt;",
    "local": ""
  },
  {
    "origin": "&gt; &amp;sizes)",
    "local": ""
  },
  {
    "origin": "virtual void",
    "local": ""
  },
  {
    "origin": "(",
    "local": ""
  },
  {
    "origin": "img,",
    "local": ""
  },
  {
    "origin": "mask,",
    "local": ""
  },
  {
    "origin": "tl)",
    "local": ""
  },
  {
    "origin": "Static Public Member Functions",
    "local": ""
  },
  {
    "origin": "static",
    "local": ""
  },
  {
    "origin": "&lt;",
    "local": ""
  },
  {
    "origin": "&gt;",
    "local": ""
  },
  {
    "origin": "(int type)",
    "local": ""
  },
  {
    "origin": "Protected Member Functions",
    "local": ""
  },
  {
    "origin": "virtual bool",
    "local": ""
  },
  {
    "origin": "(",
    "local": ""
  },
  {
    "origin": "pt)",
    "local": ""
  },
  {
    "origin": "Protected Attributes",
    "local": ""
  },
  {
    "origin": "Member Enumeration Documentation",
    "local": ""
  },
  {
    "origin": "◆",
    "local": ""
  },
  {
    "origin": "anonymous enum",
    "local": ""
  },
  {
    "origin": "anonymous enum",
    "local": ""
  },
  {
    "origin": "Enumerator",
    "local": ""
  },
  {
    "origin": "AS_IS",
    "local": ""
  },
  {
    "origin": "CROP",
    "local": ""
  },
  {
    "origin": "Constructor &amp; Destructor Documentation",
    "local": ""
  },
  {
    "origin": "◆",
    "local": ""
  },
  {
    "origin": "~Timelapser()",
    "local": ""
  },
  {
    "origin": "virtual cv::detail::Timelapser::~Timelapser",
    "local": ""
  },
  {
    "origin": "(",
    "local": ""
  },
  {
    "origin": ")",
    "local": ""
  },
  {
    "origin": "inline",
    "local": ""
  },
  {
    "origin": "virtual",
    "local": ""
  },
  {
    "origin": "Member Function Documentation",
    "local": ""
  },
  {
    "origin": "◆",
    "local": ""
  },
  {
    "origin": "createDefault()",
    "local": ""
  },
  {
    "origin": "static",
    "local": ""
  },
  {
    "origin": "&lt;",
    "local": ""
  },
  {
    "origin": "&gt; cv::detail::Timelapser::createDefault",
    "local": ""
  },
  {
    "origin": "(",
    "local": ""
  },
  {
    "origin": "int",
    "local": ""
  },
  {
    "origin": "type",
    "local": ""
  },
  {
    "origin": ")",
    "local": ""
  },
  {
    "origin": "static",
    "local": ""
  },
  {
    "origin": "Python:",
    "local": ""
  },
  {
    "origin": "retval",
    "local": ""
  },
  {
    "origin": "=",
    "local": ""
  },
  {
    "origin": "cv.detail.Timelapser_createDefault(",
    "local": ""
  },
  {
    "origin": "type",
    "local": ""
  },
  {
    "origin": ")",
    "local": ""
  },
  {
    "origin": "◆",
    "local": ""
  },
  {
    "origin": "getDst()",
    "local": ""
  },
  {
    "origin": "virtual const",
    "local": ""
  },
  {
    "origin": "&amp; cv::detail::Timelapser::getDst",
    "local": ""
  },
  {
    "origin": "(",
    "local": ""
  },
  {
    "origin": ")",
    "local": ""
  },
  {
    "origin": "inline",
    "local": ""
  },
  {
    "origin": "virtual",
    "local": ""
  },
  {
    "origin": "Python:",
    "local": ""
  },
  {
    "origin": "retval",
    "local": ""
  },
  {
    "origin": "=",
    "local": ""
  },
  {
    "origin": "cv.detail_Timelapser.getDst(",
    "local": ""
  },
  {
    "origin": ")",
    "local": ""
  },
  {
    "origin": "◆",
    "local": ""
  },
  {
    "origin": "initialize()",
    "local": ""
  },
  {
    "origin": "virtual void cv::detail::Timelapser::initialize",
    "local": ""
  },
  {
    "origin": "(",
    "local": ""
  },
  {
    "origin": "const std::vector&lt;",
    "local": ""
  },
  {
    "origin": "&gt; &amp;",
    "local": ""
  },
  {
    "origin": "corners",
    "local": ""
  },
  {
    "origin": ",",
    "local": ""
  },
  {
    "origin": "const std::vector&lt;",
    "local": ""
  },
  {
    "origin": "&gt; &amp;",
    "local": ""
  },
  {
    "origin": "sizes",
    "local": ""
  },
  {
    "origin": ")",
    "local": ""
  },
  {
    "origin": "virtual",
    "local": ""
  },
  {
    "origin": "Python:",
    "local": ""
  },
  {
    "origin": "None",
    "local": ""
  },
  {
    "origin": "=",
    "local": ""
  },
  {
    "origin": "cv.detail_Timelapser.initialize(",
    "local": ""
  },
  {
    "origin": "corners, sizes",
    "local": ""
  },
  {
    "origin": ")",
    "local": ""
  },
  {
    "origin": "Reimplemented in",
    "local": ""
  },
  {
    "origin": ".",
    "local": ""
  },
  {
    "origin": "◆",
    "local": ""
  },
  {
    "origin": "process()",
    "local": ""
  },
  {
    "origin": "virtual void cv::detail::Timelapser::process",
    "local": ""
  },
  {
    "origin": "(",
    "local": ""
  },
  {
    "origin": "img",
    "local": ""
  },
  {
    "origin": ",",
    "local": ""
  },
  {
    "origin": "mask",
    "local": ""
  },
  {
    "origin": ",",
    "local": ""
  },
  {
    "origin": "tl",
    "local": ""
  },
  {
    "origin": ")",
    "local": ""
  },
  {
    "origin": "virtual",
    "local": ""
  },
  {
    "origin": "Python:",
    "local": ""
  },
  {
    "origin": "None",
    "local": ""
  },
  {
    "origin": "=",
    "local": ""
  },
  {
    "origin": "cv.detail_Timelapser.process(",
    "local": ""
  },
  {
    "origin": "img, mask, tl",
    "local": ""
  },
  {
    "origin": ")",
    "local": ""
  },
  {
    "origin": "◆",
    "local": ""
  },
  {
    "origin": "test_point()",
    "local": ""
  },
  {
    "origin": "virtual bool cv::detail::Timelapser::test_point",
    "local": ""
  },
  {
    "origin": "(",
    "local": ""
  },
  {
    "origin": "pt",
    "local": ""
  },
  {
    "origin": ")",
    "local": ""
  },
  {
    "origin": "protected",
    "local": ""
  },
  {
    "origin": "virtual",
    "local": ""
  },
  {
    "origin": "Member Data Documentation",
    "local": ""
  },
  {
    "origin": "◆",
    "local": ""
  },
  {
    "origin": "dst_",
    "local": ""
  },
  {
    "origin": "cv::detail::Timelapser::dst_",
    "local": ""
  },
  {
    "origin": "protected",
    "local": ""
  },
  {
    "origin": "◆",
    "local": ""
  },
  {
    "origin": "dst_roi_",
    "local": ""
  },
  {
    "origin": "cv::detail::Timelapser::dst_roi_",
    "local": ""
  },
  {
    "origin": "protected",
    "local": ""
  },
  {
    "origin": "The documentation for this class was generated from the following file:",
    "local": ""
  },
  {
    "origin": "opencv2/stitching/detail/",
    "local": ""
  },
  {
    "origin": "Generated on Fri Apr 2 2021 11:36:46 for OpenCV by",
    "local": ""
  }
]