[
  {
    "origin": "OpenCV: Object Categorization",
    "local": ""
  },
  {
    "origin": "Open Source Computer Vision",
    "local": ""
  },
  {
    "origin": "Classes",
    "local": ""
  },
  {
    "origin": "Object Categorization",
    "local": ""
  },
  {
    "origin": "Classes",
    "local": ""
  },
  {
    "origin": "Class to compute an image descriptor using the",
    "local": ""
  },
  {
    "origin": "bag of visual words",
    "local": ""
  },
  {
    "origin": ".",
    "local": ""
  },
  {
    "origin": "More...",
    "local": ""
  },
  {
    "origin": "kmeans -based class to train visual vocabulary using the",
    "local": ""
  },
  {
    "origin": "bag of visual words",
    "local": ""
  },
  {
    "origin": "approach. :",
    "local": ""
  },
  {
    "origin": "More...",
    "local": ""
  },
  {
    "origin": "Abstract base class for training the",
    "local": ""
  },
  {
    "origin": "bag of visual words",
    "local": ""
  },
  {
    "origin": "vocabulary from a set of descriptors.",
    "local": ""
  },
  {
    "origin": "More...",
    "local": ""
  },
  {
    "origin": "Detailed Description",
    "local": ""
  },
  {
    "origin": "This section describes approaches based on local 2D features and used to categorize objects.",
    "local": ""
  },
  {
    "origin": "Note",
    "local": ""
  },
  {
    "origin": "A complete Bag-Of-Words sample can be found at opencv_source_code/samples/cpp/bagofwords_classification.cpp",
    "local": ""
  },
  {
    "origin": "(Python) An example using the features2D framework to perform object categorization can be found at opencv_source_code/samples/python/find_obj.py",
    "local": ""
  },
  {
    "origin": "Generated on Fri Apr 2 2021 11:36:41 for OpenCV by &#160;",
    "local": ""
  }
]