[
  {
    "origin": "OpenCV: cv::cudev::functional_detail::FloatType&lt; T &gt; Struct Template Reference",
    "local": ""
  },
  {
    "origin": "Open Source Computer Vision",
    "local": ""
  },
  {
    "origin": "Public Types",
    "local": ""
  },
  {
    "origin": "List of all members",
    "local": ""
  },
  {
    "origin": "cv::cudev::functional_detail::FloatType&lt; T &gt; Struct Template Reference",
    "local": ""
  },
  {
    "origin": "Public Types",
    "local": ""
  },
  {
    "origin": "typedef",
    "local": ""
  },
  {
    "origin": "&lt; typename",
    "local": ""
  },
  {
    "origin": "&lt; float, typename",
    "local": ""
  },
  {
    "origin": "&lt; T &gt;::elem_type &gt;::",
    "local": ""
  },
  {
    "origin": ",",
    "local": ""
  },
  {
    "origin": "&lt; T &gt;::cn &gt;::",
    "local": ""
  },
  {
    "origin": "Member Typedef Documentation",
    "local": ""
  },
  {
    "origin": "&#9670;&nbsp;",
    "local": ""
  },
  {
    "origin": "type",
    "local": ""
  },
  {
    "origin": "template&lt;typename T&gt;",
    "local": ""
  },
  {
    "origin": "typedef",
    "local": ""
  },
  {
    "origin": "&lt; typename",
    "local": ""
  },
  {
    "origin": "&lt;float, typename",
    "local": ""
  },
  {
    "origin": "&lt;T&gt;::elem_type&gt;::",
    "local": ""
  },
  {
    "origin": ",",
    "local": ""
  },
  {
    "origin": "&lt;T&gt;::cn &gt;::",
    "local": ""
  },
  {
    "origin": "&lt; T &gt;::",
    "local": ""
  },
  {
    "origin": "The documentation for this struct was generated from the following file:",
    "local": ""
  },
  {
    "origin": "opencv2/cudev/functional/",
    "local": ""
  },
  {
    "origin": "Generated on Fri Apr 2 2021 11:36:46 for OpenCV by &#160;",
    "local": ""
  }
]