[
  {
    "origin": "OpenCV: Hardware-accelerated video decoding and encoding",
    "local": ""
  },
  {
    "origin": "Open Source Computer Vision",
    "local": ""
  },
  {
    "origin": "Hardware-accelerated video decoding and encoding",
    "local": ""
  },
  {
    "origin": "This section contains information about API to control Hardware-accelerated video decoding and encoding.",
    "local": ""
  },
  {
    "origin": "Note",
    "local": ""
  },
  {
    "origin": "Check",
    "local": ""
  },
  {
    "origin": "Wiki page",
    "local": ""
  },
  {
    "origin": "for description of supported hardware / software configurations and available benchmarks",
    "local": ""
  },
  {
    "origin": "properties:",
    "local": ""
  },
  {
    "origin": "(as",
    "local": ""
  },
  {
    "origin": ")",
    "local": ""
  },
  {
    "origin": "properties:",
    "local": ""
  },
  {
    "origin": "(as",
    "local": ""
  },
  {
    "origin": ")",
    "local": ""
  },
  {
    "origin": "Properties are supported by these backends:",
    "local": ""
  },
  {
    "origin": "(Windows)",
    "local": ""
  },
  {
    "origin": "Generated on Fri Apr 2 2021 11:36:40 for OpenCV by &#160;",
    "local": ""
  }
]