[
  {
    "origin": "OpenCV: cv::gapi::own::Rect Class Reference",
    "local": "OpenCV:cv:：gapi:：own:：Rect类引用"
  },
  {
    "origin": "Open Source Computer Vision",
    "local": "开源计算机视觉"
  },
  {
    "origin": "Public Member Functions",
    "local": "公共成员职能"
  },
  {
    "origin": "Public Attributes",
    "local": "公共属性"
  },
  {
    "origin": "List of all members",
    "local": "所有成员的列表"
  },
  {
    "origin": "cv::gapi::own::Rect Class Reference",
    "local": "cv:：gapi:：own:：Rect类引用"
  },
  {
    "origin": "Public Member Functions",
    "local": "公共成员职能"
  },
  {
    "origin": "()=default",
    "local": "（）=默认值"
  },
  {
    "origin": "(int _x, int _y, int _width, int _height)",
    "local": "（整数x，整数y，整数宽度，整数高度）"
  },
  {
    "origin": "(const",
    "local": "常数"
  },
  {
    "origin": "&amp;other)",
    "local": "&amp；（其他）"
  },
  {
    "origin": "(const",
    "local": "常数"
  },
  {
    "origin": "&amp;other)",
    "local": "&amp；（其他）"
  },
  {
    "origin": "Public Attributes",
    "local": "公共属性"
  },
  {
    "origin": "height of the rectangle",
    "local": "矩形的高度"
  },
  {
    "origin": "More...",
    "local": "更多。。。"
  },
  {
    "origin": "width of the rectangle",
    "local": "矩形的宽度"
  },
  {
    "origin": "More...",
    "local": "更多。。。"
  },
  {
    "origin": "x coordinate of the top-left corner",
    "local": "左上角的x坐标"
  },
  {
    "origin": "More...",
    "local": "更多。。。"
  },
  {
    "origin": "y coordinate of the top-left corner",
    "local": "左上角y坐标"
  },
  {
    "origin": "More...",
    "local": "更多。。。"
  },
  {
    "origin": "Constructor &amp; Destructor Documentation",
    "local": "建造商和；析构函数文档"
  },
  {
    "origin": "&#9670;&nbsp;",
    "local": "&#9670;&nbsp；"
  },
  {
    "origin": "Rect()",
    "local": "右（）"
  },
  {
    "origin": "[1/3]",
    "local": "[1/3]"
  },
  {
    "origin": "cv::gapi::own::Rect::Rect",
    "local": "cv：：gapi：：own：：Rect：：Rect"
  },
  {
    "origin": "(",
    "local": "("
  },
  {
    "origin": ")",
    "local": ")"
  },
  {
    "origin": "default",
    "local": "违约"
  },
  {
    "origin": "&#9670;&nbsp;",
    "local": "&#9670;&nbsp；"
  },
  {
    "origin": "Rect()",
    "local": "右（）"
  },
  {
    "origin": "[2/3]",
    "local": "[2/3]"
  },
  {
    "origin": "cv::gapi::own::Rect::Rect",
    "local": "cv：：gapi：：own：：Rect：：Rect"
  },
  {
    "origin": "(",
    "local": "("
  },
  {
    "origin": "_x",
    "local": "_十"
  },
  {
    "origin": ",",
    "local": ","
  },
  {
    "origin": "_y",
    "local": "_是的"
  },
  {
    "origin": ",",
    "local": ","
  },
  {
    "origin": "_width",
    "local": "_宽度"
  },
  {
    "origin": ",",
    "local": ","
  },
  {
    "origin": "_height",
    "local": "_高度"
  },
  {
    "origin": ")",
    "local": ")"
  },
  {
    "origin": "inline",
    "local": "内联"
  },
  {
    "origin": "&#9670;&nbsp;",
    "local": "&#9670;&nbsp；"
  },
  {
    "origin": "Rect()",
    "local": "右（）"
  },
  {
    "origin": "[3/3]",
    "local": "[3/3]"
  },
  {
    "origin": "cv::gapi::own::Rect::Rect",
    "local": "cv：：gapi：：own：：Rect：：Rect"
  },
  {
    "origin": "(",
    "local": "("
  },
  {
    "origin": "const",
    "local": "常数"
  },
  {
    "origin": "other",
    "local": "其他"
  },
  {
    "origin": ")",
    "local": ")"
  },
  {
    "origin": "inline",
    "local": "内联"
  },
  {
    "origin": "Member Function Documentation",
    "local": "成员功能文档"
  },
  {
    "origin": "&#9670;&nbsp;",
    "local": "&#9670;&nbsp；"
  },
  {
    "origin": "operator=()",
    "local": "运算符=（）"
  },
  {
    "origin": "&amp; cv::gapi::own::Rect::operator=",
    "local": "&amp；cv:：gapi:：own:：Rect:：运算符="
  },
  {
    "origin": "(",
    "local": "("
  },
  {
    "origin": "const",
    "local": "常数"
  },
  {
    "origin": "other",
    "local": "其他"
  },
  {
    "origin": ")",
    "local": ")"
  },
  {
    "origin": "inline",
    "local": "内联"
  },
  {
    "origin": "Member Data Documentation",
    "local": "成员数据文档"
  },
  {
    "origin": "&#9670;&nbsp;",
    "local": "&#9670;&nbsp；"
  },
  {
    "origin": "height",
    "local": "高度"
  },
  {
    "origin": "height of the rectangle",
    "local": "矩形的高度"
  },
  {
    "origin": "&#9670;&nbsp;",
    "local": "&#9670;&nbsp；"
  },
  {
    "origin": "width",
    "local": "宽度"
  },
  {
    "origin": "width of the rectangle",
    "local": "矩形的宽度"
  },
  {
    "origin": "&#9670;&nbsp;",
    "local": "&#9670;&nbsp；"
  },
  {
    "origin": "x",
    "local": "十"
  },
  {
    "origin": "x coordinate of the top-left corner",
    "local": "左上角的x坐标"
  },
  {
    "origin": "&#9670;&nbsp;",
    "local": "&#9670;&nbsp；"
  },
  {
    "origin": "y",
    "local": "y"
  },
  {
    "origin": "y coordinate of the top-left corner",
    "local": "左上角y坐标"
  },
  {
    "origin": "The documentation for this class was generated from the following file:",
    "local": "此类的文档是从以下文件生成的："
  },
  {
    "origin": "opencv2/gapi/own/",
    "local": "opencv2/gapi/own公司/"
  },
  {
    "origin": "Generated on Fri Apr 2 2021 11:36:47 for OpenCV by &#160;",
    "local": "2021年4月2日星期五11:36:47为OpenCV生成，&#160；"
  }
]