[
  {
    "origin": "OpenCV: cv::InferAPIList2&lt; Net, T, Ts &gt; Struct Template Reference",
    "local": ""
  },
  {
    "origin": "Open Source Computer Vision",
    "local": ""
  },
  {
    "origin": "Public Types",
    "local": ""
  },
  {
    "origin": "List of all members",
    "local": ""
  },
  {
    "origin": "cv::InferAPIList2&lt; Net, T, Ts &gt; Struct Template Reference",
    "local": ""
  },
  {
    "origin": "Public Types",
    "local": ""
  },
  {
    "origin": "= typename std::enable_if&lt;",
    "local": ""
  },
  {
    "origin": "&lt; T &gt;::value &amp;&amp;",
    "local": ""
  },
  {
    "origin": "&lt; typename Net::InArgs, std::tuple&lt; Ts... &gt; &gt;::value, std::function&lt; typename Net::ResultL(T,",
    "local": ""
  },
  {
    "origin": "&lt; Ts &gt;...)&gt; &gt;::",
    "local": ""
  },
  {
    "origin": "Member Typedef Documentation",
    "local": ""
  },
  {
    "origin": "&#9670;&nbsp;",
    "local": ""
  },
  {
    "origin": "type",
    "local": ""
  },
  {
    "origin": "template&lt;class Net , typename T , class... Ts&gt;",
    "local": ""
  },
  {
    "origin": "using",
    "local": ""
  },
  {
    "origin": "&lt; Net, T, Ts &gt;::",
    "local": ""
  },
  {
    "origin": "= typename std::enable_if &lt;",
    "local": ""
  },
  {
    "origin": "&lt;T&gt;::value &amp;&amp;",
    "local": ""
  },
  {
    "origin": "&lt; typename Net::InArgs , std::tuple&lt;Ts...&gt; &gt;::value, std::function&lt;typename Net::ResultL(T,",
    "local": ""
  },
  {
    "origin": "&lt;Ts&gt;...)&gt; &gt;::",
    "local": ""
  },
  {
    "origin": "The documentation for this struct was generated from the following file:",
    "local": ""
  },
  {
    "origin": "opencv2/gapi/",
    "local": ""
  },
  {
    "origin": "Generated on Fri Apr 2 2021 11:36:43 for OpenCV by &#160;",
    "local": ""
  }
]