[
  {
    "origin": "OpenCV: Member List",
    "local": ""
  },
  {
    "origin": "Open Source Computer Vision",
    "local": ""
  },
  {
    "origin": "cv::ocl::ProgramSource Member List",
    "local": ""
  },
  {
    "origin": "This is the complete list of members for",
    "local": ""
  },
  {
    "origin": ", including all inherited members.",
    "local": ""
  },
  {
    "origin": "() const",
    "local": ""
  },
  {
    "origin": "inline",
    "local": ""
  },
  {
    "origin": "(const String &amp;module, const String &amp;name, const unsigned char *binary, const size_t size, const cv::String &amp;buildOptions=cv::String())",
    "local": ""
  },
  {
    "origin": "static",
    "local": ""
  },
  {
    "origin": "(const String &amp;module, const String &amp;name, const unsigned char *binary, const size_t size, const cv::String &amp;buildOptions=cv::String())",
    "local": ""
  },
  {
    "origin": "static",
    "local": ""
  },
  {
    "origin": "() const",
    "local": ""
  },
  {
    "origin": "inline",
    "local": ""
  },
  {
    "origin": "() const",
    "local": ""
  },
  {
    "origin": "typedef",
    "local": ""
  },
  {
    "origin": "friend",
    "local": ""
  },
  {
    "origin": "(const ProgramSource &amp;prog)",
    "local": ""
  },
  {
    "origin": "(ProgramSource &amp;&amp;prog) CV_NOEXCEPT",
    "local": ""
  },
  {
    "origin": "protected",
    "local": ""
  },
  {
    "origin": "() CV_NOEXCEPT",
    "local": ""
  },
  {
    "origin": "(const String &amp;module, const String &amp;name, const String &amp;codeStr, const String &amp;codeHash)",
    "local": ""
  },
  {
    "origin": "explicit",
    "local": ""
  },
  {
    "origin": "(const String &amp;prog)",
    "local": ""
  },
  {
    "origin": "explicit",
    "local": ""
  },
  {
    "origin": "(const char *prog)",
    "local": ""
  },
  {
    "origin": "explicit",
    "local": ""
  },
  {
    "origin": "(const ProgramSource &amp;prog)",
    "local": ""
  },
  {
    "origin": "(ProgramSource &amp;&amp;prog) CV_NOEXCEPT",
    "local": ""
  },
  {
    "origin": "() const",
    "local": ""
  },
  {
    "origin": "()",
    "local": ""
  },
  {
    "origin": "Generated on Fri Apr 2 2021 11:36:48 for OpenCV by &#160;",
    "local": ""
  }
]