[
  {
    "origin": "OpenCV: Member List",
    "local": ""
  },
  {
    "origin": "Open Source Computer Vision",
    "local": ""
  },
  {
    "origin": "cv::SVD Member List",
    "local": ""
  },
  {
    "origin": "This is the complete list of members for",
    "local": ""
  },
  {
    "origin": ", including all inherited members.",
    "local": ""
  },
  {
    "origin": "(InputArray w, InputArray u, InputArray vt, InputArray rhs, OutputArray dst)",
    "local": ""
  },
  {
    "origin": "static",
    "local": ""
  },
  {
    "origin": "(InputArray rhs, OutputArray dst) const",
    "local": ""
  },
  {
    "origin": "(const Matx&lt; _Tp, nm, 1 &gt; &amp;w, const Matx&lt; _Tp, m, nm &gt; &amp;u, const Matx&lt; _Tp, n, nm &gt; &amp;vt, const Matx&lt; _Tp, m, nb &gt; &amp;rhs, Matx&lt; _Tp, n, nb &gt; &amp;dst)",
    "local": ""
  },
  {
    "origin": "static",
    "local": ""
  },
  {
    "origin": "(InputArray src, OutputArray w, OutputArray u, OutputArray vt, int flags=0)",
    "local": ""
  },
  {
    "origin": "static",
    "local": ""
  },
  {
    "origin": "(InputArray src, OutputArray w, int flags=0)",
    "local": ""
  },
  {
    "origin": "static",
    "local": ""
  },
  {
    "origin": "(const Matx&lt; _Tp, m, n &gt; &amp;a, Matx&lt; _Tp, nm, 1 &gt; &amp;w, Matx&lt; _Tp, m, nm &gt; &amp;u, Matx&lt; _Tp, n, nm &gt; &amp;vt)",
    "local": ""
  },
  {
    "origin": "static",
    "local": ""
  },
  {
    "origin": "(const Matx&lt; _Tp, m, n &gt; &amp;a, Matx&lt; _Tp, nm, 1 &gt; &amp;w)",
    "local": ""
  },
  {
    "origin": "static",
    "local": ""
  },
  {
    "origin": "enum name",
    "local": ""
  },
  {
    "origin": "enum value",
    "local": ""
  },
  {
    "origin": "enum value",
    "local": ""
  },
  {
    "origin": "enum value",
    "local": ""
  },
  {
    "origin": "(InputArray src, int flags=0)",
    "local": ""
  },
  {
    "origin": "(InputArray src, OutputArray dst)",
    "local": ""
  },
  {
    "origin": "static",
    "local": ""
  },
  {
    "origin": "()",
    "local": ""
  },
  {
    "origin": "(InputArray src, int flags=0)",
    "local": ""
  },
  {
    "origin": "Generated on Fri Apr 2 2021 11:36:43 for OpenCV by &#160;",
    "local": ""
  }
]